auto_adpq/__init__.py
auto_adpq/class_format.py
auto_adpq/module.py
auto_adpq-0.3.5.dist-info/licenses/LICENSE
auto_adpq-0.3.5.dist-info/METADATA
auto_adpq-0.3.5.dist-info/WHEEL
auto_adpq-0.3.5.dist-info/top_level.txt
auto_adpq-0.3.5.dist-info/RECORD
