Metadata-Version: 2.4
Name: auto_adpq
Version: 0.3.5
Summary: Implementing auto adpq
Author-email: Tfloow <88899420+Tfloow@users.noreply.github.com>
License-Expression: Apache-2.0
Project-URL: homepage, https://thomas.debelle.be
Project-URL: documentation, https://auto-adpq.readthedocs.io/en/stable/
Project-URL: source, https://github.com/Tfloow/auto_adpq
Project-URL: download, https://pypi.org/project/auto_adpq/#files
Project-URL: tracker, https://github.com/Tfloow/auto_adpq/issues
Project-URL: release notes, https://auto-adpq.readthedocs.io/en/stable/release
Requires-Python: >=3.10
License-File: LICENSE
Requires-Dist: torch
Requires-Dist: numpy
Requires-Dist: tqdm
Requires-Dist: pydantic>=1.10
Provides-Extra: dev
Requires-Dist: pytest; extra == "dev"
Requires-Dist: coverage; extra == "dev"
Requires-Dist: build; extra == "dev"
Requires-Dist: ruff; extra == "dev"
Requires-Dist: sphinx; extra == "dev"
Requires-Dist: transformers; extra == "dev"
Requires-Dist: sphinx-multiversion; extra == "dev"
Requires-Dist: furo; extra == "dev"
Requires-Dist: twine; extra == "dev"
Requires-Dist: snakeviz; extra == "dev"
Requires-Dist: matplotlib; extra == "dev"
Dynamic: license-file
